tnt/__init__.py
tnt/py.typed
tnt/cli/__init__.py
tnt/cli/main.py
tnt/tools/__init__.py
tnt/tools/constant.py
tnt/tools/json_to_excel.py
tnt/tools/scan_services.py
tnt/tools/visualize_services.py
tnt_py-0.1.0.dist-info/METADATA
tnt_py-0.1.0.dist-info/WHEEL
tnt_py-0.1.0.dist-info/entry_points.txt
tnt_py-0.1.0.dist-info/licenses/LICENSE
tnt_py-0.1.0.dist-info/RECORD
