Metadata-Version: 2.4
Name: tnt-py
Version: 0.1.0
Summary: Scans the host for proxy dependencies
Author-email: QIN2DIM <yaoqinse@gmail.com>
License-File: LICENSE
Requires-Python: >=3.12
Requires-Dist: openpyxl>=3.1.5
Requires-Dist: pandas>=2.3.0
Requires-Dist: pydantic>=2.11.5
Requires-Dist: pyvis>=0.3.2
Requires-Dist: pyyaml>=6.0.2
Requires-Dist: typer>=0.16.0
